[
    {
        "_id": 1,
        "_mail": "juanpigonzalez72@gmail.com",
        "_sabor": "chocolate",
        "_tipo": "Crema",
        "_cantidad": "5",
        "_fecha": "2024-05-f 01:25:28",
        "_numeroPedido": 577
    },
    {
        "_id": 6,
        "_mail": "juanpigonzalez72@gmail.com",
        "_sabor": "chocolate",
        "_tipo": "Crema",
        "_cantidad": "5",
        "_fecha": "2024-05-24 01:29:04",
        "_numeroPedido": 27
    },
    {
        "_id": 7,
        "_mail": "juanpigonzalez72@gmail.com",
        "_sabor": "chocolate",
        "_tipo": "Crema",
        "_cantidad": "5",
        "_fecha": "2024-05-24 01:30:27",
        "_numeroPedido": 285
    },
    {
        "_id": 8,
        "_mail": "juanpigonzalez72@gmail.com",
        "_sabor": "chocolate",
        "_tipo": "Crema",
        "_cantidad": "5",
        "_fecha": "2024-05-24 01:32:09",
        "_numeroPedido": 977
    },
    {
        "_id": 9,
        "_mail": "juanpigonzalez72@gmail.com",
        "_sabor": "chocolate",
        "_tipo": "Crema",
        "_cantidad": "5",
        "_fecha": "2024-05-24 01:33:34",
        "_numeroPedido": 133
    },
    {
        "_id": 10,
        "_mail": "juanpigonzalez72@gmail.com",
        "_sabor": "chocolate",
        "_tipo": "Crema",
        "_cantidad": "5",
        "_fecha": "2024-05-24 01:33:50",
        "_numeroPedido": 322
    }
]